ruv/__init__.py
ruv/__version__.py
ruv/api.py
ruv/choose.py
ruv/conf.py
ruv/default_config.py
ruv/models.py
ruv-0.1.4.dist-info/DESCRIPTION.rst
ruv-0.1.4.dist-info/METADATA
ruv-0.1.4.dist-info/RECORD
ruv-0.1.4.dist-info/WHEEL
ruv-0.1.4.dist-info/entry_points.txt
ruv-0.1.4.dist-info/metadata.json
ruv-0.1.4.dist-info/top_level.txt
